Metadata-Version: 2.1
Name: py-num-methods
Version: 0.1.3
Summary: Numerical Methods and Analysis Library in Python
Home-page: 
Author: JaidevSK
Author-email: jaidevkhalane@gmail.com
License: MIT
Keywords: Numerical Methods
Classifier: Development Status :: 5 - Production/Stable
Classifier: Intended Audience :: Education
Classifier: Operating System :: Microsoft :: Windows :: Windows 11
Classifier: License :: OSI Approved :: MIT License
Classifier: Programming Language :: Python :: 3
License-File: LICENCE.txt
Requires-Dist: numpy
Requires-Dist: matplotlib
